talos/__init__.py
talos/admin/TalosAdmin.py
talos/admin/__init__.py
talos/client/Constants.py
talos/client/SimpleAbnormalCallback.py
talos/client/TalosClientConfig.py
talos/client/TalosClientConfigkeys.py
talos/client/TalosClientFactory.py
talos/client/TalosErrors.py
talos/client/TalosHttpClient.py
talos/client/TopicAbnormalCallback.py
talos/client/__init__.py
talos/client/compression/Compression.py
talos/client/compression/Gzip.py
talos/client/compression/Snappy.py
talos/client/compression/__init__.py
talos/client/serialization/MessageSerialization.py
talos/client/serialization/MessageSerializationFactory.py
talos/client/serialization/MessageSerializer.py
talos/client/serialization/MessageSerializerV1.py
talos/client/serialization/MessageSerializerV2.py
talos/client/serialization/MessageSerializerV3.py
talos/client/serialization/MessageVersion.py
talos/client/serialization/__init__.py
talos/consumer/MessageCheckpointer.py
talos/consumer/MessageProcessor.py
talos/consumer/MessageProcessorFactory.py
talos/consumer/MessageReader.py
talos/consumer/MessageReaderFactory.py
talos/consumer/PartitionFetcher.py
talos/consumer/SimpleConsumer.py
talos/consumer/TalosConsumer.py
talos/consumer/TalosConsumerConfigKeys.py
talos/consumer/TalosMessageReader.py
talos/consumer/__init__.py
talos/example/SimpleConsumerDemo.py
talos/example/SimpleProducerDemo.py
talos/example/TalosAdminDemo.py
talos/example/TalosConsumerDemo.py
talos/example/TalosProducerDemo.py
talos/example/__init__.py
talos/producer/BufferedMessageCount.py
talos/producer/PartitionMessageQueue.py
talos/producer/PartitionSender.py
talos/producer/Partitioner.py
talos/producer/ProducerNotActiveException.py
talos/producer/SimplePartitioner.py
talos/producer/SimpleProducer.py
talos/producer/TalosProducer.py
talos/producer/TalosProducerConfig.py
talos/producer/TalosProducerConfigKey.py
talos/producer/UserMessage.py
talos/producer/UserMessageCallback.py
talos_python-1.0.0.dist-info/DESCRIPTION.rst
talos_python-1.0.0.dist-info/METADATA
talos_python-1.0.0.dist-info/RECORD
talos_python-1.0.0.dist-info/WHEEL
talos_python-1.0.0.dist-info/metadata.json
talos_python-1.0.0.dist-info/top_level.txt
