Metadata-Version: 2.0
Name: talos-python
Version: 1.0.0
Summary: UNKNOWN
Home-page: UNKNOWN
Author: huyumei
Author-email: huyumei@xiaomi.com
License: UNKNOWN
Platform: UNKNOWN
Requires-Dist: atomic
Requires-Dist: cffi
Requires-Dist: python-snappy
